ercha/__init__.py
ercha/cli.py
ercha/config.py
ercha/logger.py
ercha/lzw.py
ercha/rch.py
ercha-0.1.1.dist-info/LICENSE
ercha-0.1.1.dist-info/METADATA
ercha-0.1.1.dist-info/WHEEL
ercha-0.1.1.dist-info/entry_points.txt
ercha-0.1.1.dist-info/top_level.txt
ercha-0.1.1.dist-info/RECORD
