Metadata-Version: 2.1
Name: ercha
Version: 0.1.1
Summary: Ezoa's Resource Content Handler Archiver - A Furcadia RCH file archive tool
Home-page: https://eoza.page/projects/ERCHA/
Author: Ezoa
Author-email: rawr@ezoa.page
Classifier: Programming Language :: Python :: 3
Classifier: License :: Other/Proprietary License
Classifier: Operating System :: OS Independent
Requires-Python: >=3.6
License-File: LICENSE
